{"inkVersion":20,"root":[["\n","\n",["ev",{"VAR?":"quest2_progress"},"str","^0","/str","==","/ev",{"->":".^.b","c":true},{"b":["\n",{"->":"main"},{"->":"0.15"},null]}],["ev",{"VAR?":"quest2_progress"},"str","^1","/str","==","/ev",{"->":".^.b","c":true},{"b":["\n",{"->":"progress1"},{"->":"0.15"},null]}],["ev",{"VAR?":"quest2_progress"},"str","^2","/str","==","/ev",{"->":".^.b","c":true},{"b":["\n",{"->":"progress2"},{"->":"0.15"},null]}],["ev",{"VAR?":"quest2_progress"},"str","^3","/str","==","/ev",{"->":".^.b","c":true},{"b":["\n",{"->":"progress3"},{"->":"0.15"},null]}],["ev",{"VAR?":"quest2_progress"},"str","^4","/str","==","/ev",{"->":".^.b","c":true},{"b":["\n",{"->":"progress41"},{"->":"0.15"},null]}],["ev",{"VAR?":"quest2_progress"},"str","^41","/str","==","/ev",{"->":".^.b","c":true},{"b":["\n",{"->":"progress4"},{"->":"0.15"},null]}],["ev",{"VAR?":"quest2_progress"},"str","^42","/str","==","/ev",{"->":".^.b","c":true},{"b":["\n",{"->":"progress42"},{"->":"0.15"},null]}],["ev",{"VAR?":"quest2_progress"},"str","^5","/str","==","/ev",{"->":".^.b","c":true},{"b":["\n",{"->":"progress5"},{"->":"0.15"},null]}],["ev",{"VAR?":"quest2_progress"},"str","^6","/str","==","/ev",{"->":".^.b","c":true},{"b":["\n",{"->":"normal2"},{"->":"0.15"},null]}],["ev",{"VAR?":"quest2_progress"},"str","^61","/str","==","/ev",{"->":".^.b","c":true},{"b":["\n",{"->":"progress61"},{"->":"0.15"},null]}],["ev",{"VAR?":"quest2_progress"},"str","^9","/str","==","/ev",{"->":".^.b","c":true},{"b":["\n",{"->":"progress6"},{"->":"0.15"},null]}],["ev",{"VAR?":"quest2_progress"},"str","^10","/str","==","/ev",{"->":".^.b","c":true},{"b":["\n",{"->":"progress7"},{"->":"0.15"},null]}],["ev",{"VAR?":"quest2_progress"},"str","^11","/str","==","/ev",{"->":".^.b","c":true},{"b":["\n",{"->":"progress8"},{"->":"0.15"},null]}],"nop","\n",{"->":"normal"},["done",{"#f":5,"#n":"g-0"}],null],"done",{"normal":["^You see they are still practicing.",{"#":"logtype:mono"},"\n","end",{"#f":1}],"normal2":["^I should wait for him to return.",{"#":"logtype:di"},{"#":"speaker:Tim"},{"#":"portrait:portrait_schoolnpc"},"\n","end",{"#f":1}],"main":[["^(You feel a faint shadowy aura from the person, do you want to try talking to him?)",{"#":"logtype:mono"},"\n","ev","str","^Yes","/str","/ev",{"*":".^.c-0","flg":4},"ev","str","^No","/str","/ev",{"*":".^.c-1","flg":4},{"c-0":["\n",{"->":"progress1"},{"#f":5}],"c-1":["\n","^Maybe I need some time to prepare","\n","end",{"#f":5}]}],{"#f":1}],"progress1":[["ev","str","^1","/str","/ev",{"VAR=":"quest2_progress","re":true},"^(Maybe we shouldn't be talking directly to him)",{"#":"logtype:di"},{"#":"speaker:Yuuki"},{"#":"portrait:portrait_player"},{"#":"questtrigger:start"},{"#":"quest_id:2"},"\n","^Why?",{"#":"speaker:???"},{"#":"portrait:portrait_npc_mysterious"},"\n","^(Won't people feel strange if he is talking to himself?)",{"#":"speaker:Yuuki"},{"#":"portrait:portrait_player"},"\n","^(Like people can't really see me, and there are people around here)","\n","^(Can you do the linking thing?)","\n","^Yeah sure.",{"#":"speaker:???"},{"#":"portrait:portrait_npc_mysterious"},"\n","^Are you ready?","\n","ev","str","^Yes","/str","/ev",{"*":".^.c-0","flg":4},"ev","str","^No","/str","/ev",{"*":".^.c-1","flg":4},{"c-0":["\n","ev","str","^2","/str","/ev",{"VAR=":"quest2_progress","re":true},"^You feel a strange power linking you and the person.",{"#":"logtype:mono"},{"#":"portal:SQ_2_backstory"},"\n","end",{"#f":5}],"c-1":["\n","^Maybe I need some time to prepare","\n","end",{"#f":5}]}],{"#f":1}],"progress2":[["^Well seems like he probably have selective mutism.",{"#":"logtype:di"},{"#":"speaker:???"},{"#":"portrait:portrait_npc_mysterious"},"\n","^Do you know about selective mutism?","\n","ev","str","^Yes","/str","/ev",{"*":".^.c-0","flg":4},"ev","str","^No","/str","/ev",{"*":".^.c-1","flg":4},{"c-0":["\n",{"->":"selectivem1"},{"#f":5}],"c-1":["\n",{"->":"selectivem1"},{"#f":5}]}],{"#f":1}],"selectivem1":[["^Which is the correct definition for selective mutism?",{"#":"logtype:di"},{"#":"speaker:???"},{"#":"portrait:portrait_npc_mysterious"},"\n","ev","str","^A type of anxiety disorder that affects a one's ability to speak in some situations but not others.","/str","/ev",{"*":".^.c-0","flg":4},"ev","str","^A long-term and overwhelming fear of social situations.","/str","/ev",{"*":".^.c-1","flg":4},{"c-0":["\n","^Correct. It usually starts during childhood and, if left untreated, can persist into adulthood.","\n","^Also this is a rather complex case which require to be treated with care.","\n",{"->":"selectivem2"},{"#f":5}],"c-1":["\n","^This is a little too general and is more to definition of social anxiety.","\n","^But it have some similarities to selective mutism.","\n",{"->":"selectivem2"},{"#f":5}]}],{"#f":1}],"selectivem2":["^Maybe we could prepare some reward.",{"#":"logtype:di"},{"#":"speaker:???"},{"#":"portrait:portrait_npc_mysterious"},"\n","^Using the reward to go for exposure-based behavioural therapy.","\n","^Of course this would be ideal if it's done with a professional, but thats the current option we have now.","\n","^(What’s that?)",{"#":"speaker:Yuuki"},{"#":"portrait:portrait_player"},"\n","^We can first decide on an exposure hierarchy.",{"#":"speaker:???"},{"#":"portrait:portrait_npc_mysterious"},"\n","^It's like creating a list of tasks that is related to his problem","\n","^Which in this case is interaction with others.","\n","^Working from the easy tasks and gradually increasing more exposure.","\n","^Then provide rewards for each task that was completed to keep the motivation going.","\n","^Slowly increasing his confidence and help him getting used to interacting with others.","\n","^(Hmm sounds good, maybe we can try that)",{"#":"speaker:Yuuki"},{"#":"portrait:portrait_player"},"\n","^Ok now that we have some idea about his problem, so let's try speaking with him.",{"#":"speaker:???"},{"#":"portrait:portrait_npc_mysterious"},"\n",{"->":"progress21"},{"#f":1}],"progress21":["^Hey there.",{"#":"logtype:di"},{"#":"speaker:Yuuki"},{"#":"portrait:portrait_player"},"\n","^...?! I-… uh… …",{"#":"speaker:Tim"},{"#":"portrait:portrait_schoolnpc"},"\n","^The boy seemed to start panicking and is nervous about your presence as he tries to speak",{"#":"logtype:mono"},"\n","^You could already feel the shadow energy is growing rapidly","\n","^Seems like we have no choice but to help him calm down.",{"#":"logtype:di"},{"#":"speaker:???"},{"#":"portrait:portrait_npc_mysterious"},"\n","^I’ll use my powers to calm him down first, but it would be temporary as it doesn’t really solve the root cause.","\n","^Now face your hands towards him.","\n","^As you lift your hands and aim towards the him, your hand starts to emit a weak but warm light.",{"#":"logtype:mono"},{"#":"playse:heal"},"\n","^You can feel the shadow energy has subsided.","\n","^You feeling better?",{"#":"logtype:di"},{"#":"speaker:Yuuki"},{"#":"portrait:portrait_player"},"\n","^...yes ...?! I- I can speak...",{"#":"speaker:Tim"},{"#":"portrait:portrait_schoolnpc"},"\n","^Great!",{"#":"speaker:Yuuki"},{"#":"portrait:portrait_player"},"\n","^Wh- who are you…? My parents told me not to talk to strangers.",{"#":"speaker:Tim"},{"#":"portrait:portrait_schoolnpc"},"\n","^But you are already talking to me.",{"#":"speaker:Yuuki"},{"#":"portrait:portrait_player"},"\n","^Ah…!",{"#":"speaker:Tim"},{"#":"portrait:portrait_schoolnpc"},"\n","^He then closes his mouth with both hands",{"#":"logtype:mono"},"\n","^Ahahaha, don't worry I won't do any harm to you.",{"#":"logtype:di"},{"#":"speaker:Yuuki"},{"#":"portrait:portrait_player"},"\n","^Actually, I am a magician that helps to cheer people up and you seem to be a little down.","\n","^Currently we are communicating directly in your mind, so that you won't be talking to yourself in front of others.","\n","^Oh... now that you've mentioned about it... Bu- but how did you calm me down?",{"#":"speaker:Tim"},{"#":"portrait:portrait_schoolnpc"},"\n","^Well I did say that I am a magician so thats my magic.",{"#":"speaker:Yuuki"},{"#":"portrait:portrait_player"},"\n","^Wow so that light was actually magic?! Ca- can you show me again?",{"#":"speaker:Tim"},{"#":"portrait:portrait_schoolnpc"},"\n","^Looks like he is more curious with the magic rather than why there is a person directly talking in his mind.",{"#":"logtype:mono"},"\n","^(Hey, use that magic again. I need to prove myself)",{"#":"logtype:di"},{"#":"speaker:Yuuki"},{"#":"portrait:portrait_player"},"\n","^My powers aren’t for performance… but fine…",{"#":"speaker:???"},{"#":"portrait:portrait_npc_mysterious"},"\n","^Your hands start to emit light again",{"#":"logtype:mono"},{"#":"playse:heal"},"\n","^Wow… that’s so cool. It’s like magic from the fantasy movies!",{"#":"logtype:di"},{"#":"speaker:Tim"},{"#":"portrait:portrait_schoolnpc"},"\n","^Yeah, it is actually a special small magic that helps people to calm down.",{"#":"speaker:Yuuki"},{"#":"portrait:portrait_player"},"\n","^Ca- can you teach me that magic…?",{"#":"speaker:Tim"},{"#":"portrait:portrait_schoolnpc"},"\n","^…I usually would get really nervous in front of people","\n","^But somehow your magic was able to help me calm down.","\n","^This is probably my first time being able to properly talk to other people…","\n","^So I really want to learn it so I can speak with other people normally…","\n","^Yeah sure but the magic only has temporary effect","\n","^So maybe I can teach you a different magic which is better.",{"#":"speaker:Yuuki"},{"#":"portrait:portrait_player"},"\n","^Really? Th- thank you…!",{"#":"speaker:Tim"},{"#":"portrait:portrait_schoolnpc"},"\n","^Of course, I already told you that I am a magician that cheers people up right?",{"#":"speaker:Yuuki"},{"#":"portrait:portrait_player"},"\n","^Before that I need to prepare some stuff, I’ll be back.","\n","^Okay let's go, I'll break the link and send you back.",{"#":"speaker:???"},{"#":"portrait:portrait_npc_mysterious"},"\n","^Ok…? He’s already gone…",{"#":"speaker:Tim"},{"#":"portrait:portrait_schoolnpc"},{"#":"questtrigger:proceedprogress"},{"#":"questtrigger_type:force"},{"#":"quest_id:2"},"\n","ev","str","^3","/str","/ev",{"VAR=":"quest2_progress","re":true},"end",{"#f":1}],"progress3":["^(Maybe we can start from deciding on a list of tasks.)",{"#":"logtype:di"},{"#":"speaker:Yuuki"},{"#":"portrait:portrait_player"},"\n","^(Hmm maybe he can start from interacting with me without the help of the magic)","\n","^(As for the order of the task…)","\n",{"->":"quiz1"},{"#f":1}],"quiz1":[["^What's first...",{"#":"logtype:di"},{"#":"speaker:Yuuki"},{"#":"portrait:portrait_player"},"\n","ev","str","^Try to answer close-ended question","/str","/ev",{"*":".^.c-0","flg":20},"ev","str","^Try to answer open-ended question","/str","/ev",{"*":".^.c-1","flg":20},"ev","str","^Make eye contact with me","/str","/ev",{"*":".^.c-2","flg":20},"ev","str","^Try to whisper “Hi” to me","/str","/ev",{"*":".^.c-3","flg":20},{"c-0":["\n","^Maybe it's still too early for this.","\n",{"->":"quiz1"},{"#f":5}],"c-1":["\n","^Maybe it's still too early for this.","\n",{"->":"quiz1"},{"#f":5}],"c-2":["\n","^Making eye contact should be easier than the other tasks.","\n",{"->":"quiz2"},{"#f":5}],"c-3":["\n","^Maybe it's still too early for this.","\n",{"->":"quiz1"},{"#f":5}]}],{"#f":1}],"quiz2":[["^What's next...",{"#":"logtype:di"},{"#":"speaker:Yuuki"},{"#":"portrait:portrait_player"},"\n","ev","str","^Try to answer open-ended question","/str","/ev",{"*":".^.c-0","flg":20},"ev","str","^Try to answer close-ended question","/str","/ev",{"*":".^.c-1","flg":20},"ev","str","^Try to whisper “Hi” to me","/str","/ev",{"*":".^.c-2","flg":20},{"c-0":["\n","^Maybe it's still too early for this.","\n",{"->":"quiz2"},{"#f":5}],"c-1":["\n","^Maybe it's still too early for this.","\n",{"->":"quiz2"},{"#f":5}],"c-2":["\n","^Trying to speak a simple word should be easier than answering questions.","\n",{"->":"quiz3"},{"#f":5}]}],{"#f":1}],"quiz3":[["^Then...",{"#":"logtype:di"},{"#":"speaker:Yuuki"},{"#":"portrait:portrait_player"},"\n","ev","str","^Try to answer close-ended question","/str","/ev",{"*":".^.c-0","flg":20},"ev","str","^Try to answer open-ended question","/str","/ev",{"*":".^.c-1","flg":20},{"c-0":["\n","^Answering a close-ended question with predefined answer should be easier.","\n","^Since open-ended question require thinking and there is no definite answer.","\n",{"->":"progress31"},{"#f":5}],"c-1":["\n","^Maybe it's still too early for this.","\n",{"->":"quiz3"},{"#f":5}]}],{"#f":1}],"progress31":["^(Basically, try to make eye contact, try to whisper “hi” to me)",{"#":"logtype:di"},{"#":"speaker:Yuuki"},{"#":"portrait:portrait_player"},"\n","^(Then try to answer close-ended question and finally try to answer open-ended question.)","\n","^Seems fine to me.",{"#":"speaker:???"},{"#":"portrait:portrait_npc_mysterious"},"\n","^(Before that, we need to know what he likes for the reward)",{"#":"speaker:Yuuki"},{"#":"portrait:portrait_player"},"\n","^It seems like he likes chocolate",{"#":"speaker:???"},{"#":"portrait:portrait_npc_mysterious"},"\n","^(So we need to find chocolate… but how do we get it)",{"#":"speaker:Yuuki"},{"#":"portrait:portrait_player"},"\n","^Well, you can go to the school convenience store to get it.",{"#":"speaker:???"},{"#":"portrait:portrait_npc_mysterious"},"\n","^The one near the portal.","\n","^(But I don’t have money on me…)",{"#":"speaker:Yuuki"},{"#":"portrait:portrait_player"},"\n","^I can give you some money.",{"#":"speaker:???"},{"#":"portrait:portrait_npc_mysterious"},"\n","^(Why do you even have money, you don’t really need it right?)",{"#":"speaker:Yuuki"},{"#":"portrait:portrait_player"},"\n","^Well I don’t but that doesn’t mean that I can’t have it. Don’t worry the money is really mine, I guarantee it.",{"#":"speaker:???"},{"#":"portrait:portrait_npc_mysterious"},"\n","^(...Ok then)",{"#":"speaker:Yuuki"},{"#":"portrait:portrait_player"},"\n","^You obtained some money",{"#":"logtype:mono"},{"#":"getitem:item4"},{"#":"questtrigger:proceedprogress"},{"#":"questtrigger_type:force"},{"#":"quest_id:2"},"\n","ev","str","^4","/str","/ev",{"VAR=":"quest2_progress","re":true},"end",{"#f":1}],"progress41":["^I should wait for him to return...",{"#":"logtype:di"},{"#":"speaker:Tim"},{"#":"portrait:portrait_schoolnpc"},"\n","end",{"#f":1}],"progress4":[["^Hi, I am back",{"#":"logtype:di"},{"#":"speaker:Yuuki"},{"#":"portrait:portrait_player"},"\n","^Welcome back... I can see you, but seems like no one noticed you",{"#":"speaker:Tim"},{"#":"portrait:portrait_schoolnpc"},"\n","^I thought that making you visible to him would be easier to simulate real situations.",{"#":"speaker:???"},{"#":"portrait:portrait_npc_mysterious"},"\n","^Don't worry other people can't see you for now.","\n","^Yeah It's my magic, and like this would be better for the communication simulation.",{"#":"speaker:Yuuki"},{"#":"portrait:portrait_player"},"\n","^Oh ok...so the preparations are ready…?",{"#":"speaker:Tim"},{"#":"portrait:portrait_schoolnpc"},"\n","ev","str","^Yeah","/str","/ev",{"*":".^.c-0","flg":4},"ev","str","^Not yet","/str","/ev",{"*":".^.c-1","flg":4},{"c-0":["\n","^(Let me make sure...)",{"#":"speaker:Yuuki"},{"#":"portrait:portrait_player"},{"#":"questtrigger:proceedprogress"},{"#":"quest_id:2"},"\n","ev",{"VAR?":"proceed_progress"},"/ev",[{"->":".^.b","c":true},{"b":["\n","^You took out the bag of chocolate",{"#":"speaker:Yuuki"},{"#":"portrait:portrait_player"},"\n","^Is that chocolate...?",{"#":"speaker:Tim"},{"#":"portrait:portrait_schoolnpc"},"\n","^You then explain about the plan",{"#":"logtype:mono"},"\n","^That doesn’t really sound like magic to me…",{"#":"logtype:di"},{"#":"speaker:Tim"},{"#":"portrait:portrait_schoolnpc"},"\n","^He doesn’t seem as excited as before when he was told that he will be taught about magic.",{"#":"logtype:mono"},"\n","^You will be rewarded with chocolate for each task completed ",{"#":"logtype:di"},{"#":"speaker:Yuuki"},{"#":"portrait:portrait_player"},"\n","^...! ...How did you know I like chocolate",{"#":"speaker:Tim"},{"#":"portrait:portrait_schoolnpc"},"\n","^Well it’s magic. So would you like to try?",{"#":"speaker:Yuuki"},{"#":"portrait:portrait_player"},"\n","^...I’ll believe you for once.",{"#":"speaker:Tim"},{"#":"portrait:portrait_schoolnpc"},"\n","^You can see that he is drooling knowing that he is attracted by the reward as you showed him the chocolate.",{"#":"logtype:mono"},"\n","^Great! Let’s start. So I will release the magic casted on you, but don’t worry I will help you to calm down if needed.",{"#":"logtype:di"},{"#":"speaker:Yuuki"},{"#":"portrait:portrait_player"},"\n","^Also you can take your time and keep trying, even if you fail you won’t lose your reward.","\n","^O- okay… I am ready.",{"#":"speaker:Tim"},{"#":"portrait:portrait_schoolnpc"},"\n","^You put your hands in front of him and mysterious person removes the magic casted on him.",{"#":"logtype:mono"},"\n","ev","str","^42","/str","/ev",{"VAR=":"quest2_progress","re":true},"ev",false,"/ev",{"VAR=":"proceed_progress","re":true},"end",{"->":".^.^.^.12"},null]}],[{"->":".^.b"},{"b":["\n","^(I haven't finish searching yet)",{"#":"logtype:di"},{"#":"speaker:Yuuki"},{"#":"portrait:portrait_player"},"\n",{"->":".^.^.^.12"},null]}],"nop","\n","end",{"#f":5}],"c-1":["\n","end",{"#f":5}]}],{"#f":1}],"progress42":["^After a while, even though it took some time, he was able to clear all the tasks.",{"#":"logtype:mono"},"\n","^Good job! You did great!",{"#":"logtype:di"},{"#":"speaker:Yuuki"},{"#":"portrait:portrait_player"},{"#":"removeitem:item5"},"\n","^Th- thank… you…, I feel… a little more… confident.",{"#":"speaker:Tim"},{"#":"portrait:portrait_schoolnpc"},{"#":"getitem:item6"},"\n","^Maybe you can now try to communicate with others.",{"#":"speaker:Yuuki"},{"#":"portrait:portrait_player"},"\n","^O- ok… I think… I can try…",{"#":"speaker:Tim"},{"#":"portrait:portrait_schoolnpc"},"\n","^I’ll go prepare, wait me for a while.",{"#":"speaker:Yuuki"},{"#":"portrait:portrait_player"},"\n","^The myeterious person used his powers to make you invisible",{"#":"logtype:mono"},"\n","^O- ok… he’s gone again…",{"#":"logtype:di"},{"#":"speaker:Tim"},{"#":"portrait:portrait_schoolnpc"},"\n","ev","str","^5","/str","/ev",{"VAR=":"quest2_progress","re":true},"end",{"#f":1}],"progress5":["^(If that’s the case then maybe we need new tasks…)!",{"#":"logtype:di"},{"#":"speaker:Yuuki"},{"#":"portrait:portrait_player"},"\n",{"->":"quiz4"},{"#f":1}],"quiz4":[["^First...!",{"#":"logtype:di"},{"#":"speaker:Yuuki"},{"#":"portrait:portrait_player"},"\n","ev","str","^Try to whisper to a new peer with me","/str","/ev",{"*":".^.c-0","flg":20},"ev","str","^Try to whisper to a familiar peer with me","/str","/ev",{"*":".^.c-1","flg":20},"ev","str","^Try to whisper to a new peer alone","/str","/ev",{"*":".^.c-2","flg":20},"ev","str","^Try to whisper to a familiar peer alone","/str","/ev",{"*":".^.c-3","flg":20},{"c-0":["\n","^Maybe it's still too early for this.","\n",{"->":"quiz4"},{"#f":5}],"c-1":["\n","^Maybe he can start from trying to talk to a familiar peer with someone he can talk to.","\n","^Which in this case would be myself.","\n",{"->":"quiz5"},{"#f":5}],"c-2":["\n","^Maybe it's still too early for this.","\n",{"->":"quiz4"},{"#f":5}],"c-3":["\n","^Maybe it's still too early for this.","\n",{"->":"quiz4"},{"#f":5}]}],{"#f":1}],"quiz5":[["^Then...!",{"#":"logtype:di"},{"#":"speaker:Yuuki"},{"#":"portrait:portrait_player"},"\n","ev","str","^Try to whisper to a familiar peer alone","/str","/ev",{"*":".^.c-0","flg":20},"ev","str","^Try to whisper to a new peer with me","/str","/ev",{"*":".^.c-1","flg":20},"ev","str","^Try to whisper to a new peer alone","/str","/ev",{"*":".^.c-2","flg":20},{"c-0":["\n","^Then he can try to do it alone.","\n",{"->":"quiz6"},{"#f":5}],"c-1":["\n","^Maybe it's still too early for this.","\n",{"->":"quiz5"},{"#f":5}],"c-2":["\n","^Maybe it's still too early for this.","\n",{"->":"quiz5"},{"#f":5}]}],{"#f":1}],"quiz6":[["^Next...!",{"#":"logtype:di"},{"#":"speaker:Yuuki"},{"#":"portrait:portrait_player"},"\n","ev","str","^Try to whisper to a new peer alone","/str","/ev",{"*":".^.c-0","flg":20},"ev","str","^Try to whisper to a new peer with me","/str","/ev",{"*":".^.c-1","flg":20},{"c-0":["\n","^Maybe it's still too early for this.","\n",{"->":"quiz6"},{"#f":5}],"c-1":["\n","^Finally, he will try to talk to a new peer with me and then trying it alone.","\n",{"->":"progress51"},{"#f":5}]}],{"#f":1}],"progress51":["^(Basically it would be talk to someone familiar with me, then trying it alone.)!",{"#":"logtype:di"},{"#":"speaker:Yuuki"},{"#":"portrait:portrait_player"},"\n","^(After he is confident enough, he can try to talk to someone new together and then trying it alone)","\n","^(Currently there’s still enough reward, but we need to find some help from other people)","\n","^I can feel that the girl at the front of the classroom is rather familiar with him, maybe we can ask her to help.",{"#":"speaker:???"},{"#":"portrait:portrait_npc_mysterious"},"\n","^Well we can try to ask.",{"#":"speaker:Yuuki"},{"#":"portrait:portrait_player"},"\n","^Let's go then",{"#":"speaker:???"},{"#":"portrait:portrait_npc_mysterious"},"\n","ev","str","^6","/str","/ev",{"VAR=":"quest2_progress","re":true},"end",{"#f":1}],"progress6":["^I am back again",{"#":"logtype:di"},{"#":"speaker:Yuuki"},{"#":"portrait:portrait_player"},"\n","^W- welcome back...",{"#":"speaker:Tim"},{"#":"portrait:portrait_schoolnpc"},"\n","^So for the next tasks...",{"#":"speaker:Yuuki"},{"#":"portrait:portrait_player"},"\n","^You explained about your next plan.",{"#":"logtype:mono"},"\n","^...but w- where do we find people... to do this...?",{"#":"logtype:di"},{"#":"speaker:Tim"},{"#":"portrait:portrait_schoolnpc"},"\n","^Don't worry I brought some help for that",{"#":"speaker:Yuuki"},{"#":"portrait:portrait_player"},"\n","^I think she will be here soon","\n","^Just when you mentioned about her, she arrived",{"#":"logtype:mono"},"\n","ev","str","^61","/str","/ev",{"VAR=":"quest2_progress","re":true},"end",{"#f":1}],"progress61":["^…! Umm… h-… …",{"#":"logtype:di"},{"#":"speaker:Tim"},{"#":"portrait:portrait_schoolnpc"},"\n","^He starts to tense up but despite that he tries to talk.",{"#":"logtype:mono"},"\n","^I already heard everything from that person.",{"#":"logtype:di"},{"#":"speaker:Sally"},{"#":"portrait:portrait_schoolnpcgirl"},"\n","^O- ok...",{"#":"speaker:Tim"},{"#":"portrait:portrait_schoolnpc"},"\n","^If you’re ready then let’s start",{"#":"speaker:Yuuki"},{"#":"portrait:portrait_player"},"\n","^I-… I am… ready…!",{"#":"speaker:Tim"},{"#":"portrait:portrait_schoolnpc"},"\n","^And we proceeded with the tasks.",{"#":"logtype:mono"},"\n","ev","str","^10","/str","/ev",{"VAR=":"quest2_progress","re":true},"end",{"#f":1}],"progress7":["^Ok I think that should be fine, good work everybody.",{"#":"logtype:di"},{"#":"speaker:Yuuki"},{"#":"portrait:portrait_player"},{"#":"removeitem:item6"},"\n","^Even though it took longer than before but he managed to finish all of it.",{"#":"logtype:mono"},"\n","^Good job, you cleared all the tasks! You have made your first step!",{"#":"logtype:di"},{"#":"speaker:Yuuki"},{"#":"portrait:portrait_player"},"\n","^Th- thank… you…",{"#":"speaker:Tim"},{"#":"portrait:portrait_schoolnpc"},"\n","^I- I think I feel… more confident… even though I… still can’t speak well… but I know I am improving…","\n","^Good, I believe that if you keep practicing, you definitely can speak normally with others soon.",{"#":"speaker:Yuuki"},{"#":"portrait:portrait_player"},"\n","^But you don’t have to force yourself, just try it with your own pace.","\n","ev","str","^11","/str","/ev",{"VAR=":"quest2_progress","re":true},"end",{"#f":1}],"progress8":["ev","str","^12","/str","/ev",{"VAR=":"quest2_progress","re":true},"ev",true,"/ev",{"VAR=":"shadow2_escaped","re":true},"^Hey the shadow enemy has escaped, after it.",{"#":"logtype:di"},{"#":"speaker:???"},{"#":"portrait:portrait_npc_mysterious"},"\n","^I think I have to leave already, I suddenly remembered that I have some urgent matter.",{"#":"speaker:Yuuki"},{"#":"portrait:portrait_player"},{"#":"questtrigger:proceedprogress"},{"#":"questtrigger_type:force"},{"#":"quest_id:2"},"\n","^Good luck on practicing the “magic” that I have taught you.","\n","^Wa- h- he's gone...",{"#":"speaker:Tim"},{"#":"portrait:portrait_schoolnpc"},{"#":"questtrigger:proceedprogress"},{"#":"questtrigger_type:force"},{"#":"quest_id:103"},"\n","^The mysterious person has made you invisible again, allowing you to focus on the chase.",{"#":"logtype:mono"},{"#":"questtrigger:complete"},{"#":"quest_id:2"},"\n","ev","str","^10","/str","/ev",{"VAR=":"mainquest_progress","re":true},"end",{"#f":1}],"completeQuest":[{"temp=":"complete"},{"temp=":"questID"},"ev",{"VAR?":"questID"},"/ev",["du","ev",1,"==","/ev",{"->":".^.b","c":true},{"b":["pop","\n","ev",{"VAR?":"complete"},"str","^True","/str","==","/ev",[{"->":".^.b","c":true},{"b":["\n","ev",true,"/ev",{"VAR=":"quest1_complete","re":true},"ev","str","^complete","/str","/ev",{"VAR=":"quest1_status","re":true},{"->":".^.^.^.10"},null]}],"nop","\n",{"->":".^.^.^.11"},null]}],["du","ev",102,"==","/ev",{"->":".^.b","c":true},{"b":["pop","\n","ev",{"VAR?":"complete"},"str","^True","/str","==","/ev",[{"->":".^.b","c":true},{"b":["\n","ev",true,"/ev",{"VAR=":"quest102_complete","re":true},"ev","str","^complete","/str","/ev",{"VAR=":"quest102_status","re":true},{"->":".^.^.^.10"},null]}],"nop","\n",{"->":".^.^.^.11"},null]}],["du","ev",2,"==","/ev",{"->":".^.b","c":true},{"b":["pop","\n","ev",{"VAR?":"complete"},"str","^True","/str","==","/ev",[{"->":".^.b","c":true},{"b":["\n","ev",true,"/ev",{"VAR=":"quest2_complete","re":true},"ev","str","^complete","/str","/ev",{"VAR=":"quest2_status","re":true},{"->":".^.^.^.10"},null]}],"nop","\n",{"->":".^.^.^.11"},null]}],["du","ev",103,"==","/ev",{"->":".^.b","c":true},{"b":["pop","\n","ev",{"VAR?":"complete"},"str","^True","/str","==","/ev",[{"->":".^.b","c":true},{"b":["\n","ev",true,"/ev",{"VAR=":"quest103_complete","re":true},"ev","str","^complete","/str","/ev",{"VAR=":"quest103_status","re":true},{"->":".^.^.^.10"},null]}],"nop","\n",{"->":".^.^.^.11"},null]}],["du","ev",3,"==","/ev",{"->":".^.b","c":true},{"b":["pop","\n","ev",{"VAR?":"complete"},"str","^True","/str","==","/ev",[{"->":".^.b","c":true},{"b":["\n","ev",true,"/ev",{"VAR=":"quest3_complete","re":true},"ev","str","^complete","/str","/ev",{"VAR=":"quest3_status","re":true},{"->":".^.^.^.10"},null]}],"nop","\n",{"->":".^.^.^.11"},null]}],"pop","nop","\n",{"#f":1}],"checkRequirement":[{"temp=":"complete"},{"temp=":"questID"},"ev",{"VAR?":"questID"},"/ev",["du","ev",1,"==","/ev",{"->":".^.b","c":true},{"b":["pop","\n","ev",{"VAR?":"complete"},"str","^True","/str","==","/ev",[{"->":".^.b","c":true},{"b":["\n","ev",true,"/ev",{"VAR=":"proceed_progress","re":true},{"->":".^.^.^.11"},null]}],[{"->":".^.b"},{"b":["\n","ev",false,"/ev",{"VAR=":"proceed_progress","re":true},{"->":".^.^.^.11"},null]}],"nop","\n",{"->":".^.^.^.11"},null]}],["du","ev",102,"==","/ev",{"->":".^.b","c":true},{"b":["pop","\n","ev",{"VAR?":"complete"},"str","^True","/str","==","/ev",[{"->":".^.b","c":true},{"b":["\n","ev",true,"/ev",{"VAR=":"proceed_progress","re":true},{"->":".^.^.^.11"},null]}],[{"->":".^.b"},{"b":["\n","ev",false,"/ev",{"VAR=":"proceed_progress","re":true},{"->":".^.^.^.11"},null]}],"nop","\n",{"->":".^.^.^.11"},null]}],["du","ev",2,"==","/ev",{"->":".^.b","c":true},{"b":["pop","\n","ev",{"VAR?":"complete"},"str","^True","/str","==","/ev",[{"->":".^.b","c":true},{"b":["\n","ev",true,"/ev",{"VAR=":"proceed_progress","re":true},{"->":".^.^.^.11"},null]}],[{"->":".^.b"},{"b":["\n","ev",false,"/ev",{"VAR=":"proceed_progress","re":true},{"->":".^.^.^.11"},null]}],"nop","\n",{"->":".^.^.^.11"},null]}],["du","ev",103,"==","/ev",{"->":".^.b","c":true},{"b":["pop","\n","ev",{"VAR?":"complete"},"str","^True","/str","==","/ev",[{"->":".^.b","c":true},{"b":["\n","ev",true,"/ev",{"VAR=":"proceed_progress","re":true},{"->":".^.^.^.11"},null]}],[{"->":".^.b"},{"b":["\n","ev",false,"/ev",{"VAR=":"proceed_progress","re":true},{"->":".^.^.^.11"},null]}],"nop","\n",{"->":".^.^.^.11"},null]}],["du","ev",3,"==","/ev",{"->":".^.b","c":true},{"b":["pop","\n","ev",{"VAR?":"complete"},"str","^True","/str","==","/ev",[{"->":".^.b","c":true},{"b":["\n","ev",true,"/ev",{"VAR=":"proceed_progress","re":true},{"->":".^.^.^.11"},null]}],[{"->":".^.b"},{"b":["\n","ev",false,"/ev",{"VAR=":"proceed_progress","re":true},{"->":".^.^.^.11"},null]}],"nop","\n",{"->":".^.^.^.11"},null]}],"pop","nop","\n",{"#f":1}],"global decl":["ev",false,{"VAR=":"proceed_progress"},false,{"VAR=":"gate_portal1"},false,{"VAR=":"gate_portal2"},false,{"VAR=":"gate_portal3"},false,{"VAR=":"startstage2"},false,{"VAR=":"void_checked"},false,{"VAR=":"crystal_checked"},false,{"VAR=":"gate_checked"},false,{"VAR=":"areatrigger102_1"},false,{"VAR=":"areatrigger103"},false,{"VAR=":"fountain_checked"},false,{"VAR=":"shopchocolate_bought"},false,{"VAR=":"girlhelped"},false,{"VAR=":"shadow2_escaped"},false,{"VAR=":"shadow2_defeated"},false,{"VAR=":"shadow3_escaped"},false,{"VAR=":"shadow3_defeated"},false,{"VAR=":"shadow3_first_defeated"},false,{"VAR=":"playground1_checked"},false,{"VAR=":"playground2_checked"},false,{"VAR=":"playground3_checked"},false,{"VAR=":"playground4_checked"},false,{"VAR=":"playground5_checked"},false,{"VAR=":"window1_checked"},false,{"VAR=":"window2_checked"},0,{"VAR=":"window_checked_count"},0,{"VAR=":"playground_checked_count"},"str","^none","/str",{"VAR=":"mainquest_status"},"str","^0","/str",{"VAR=":"mainquest_progress"},false,{"VAR=":"mainquest_complete"},"str","^none","/str",{"VAR=":"quest1_status"},"str","^0","/str",{"VAR=":"quest1_progress"},false,{"VAR=":"quest1_complete"},"str","^none","/str",{"VAR=":"quest2_status"},"str","^0","/str",{"VAR=":"quest2_progress"},false,{"VAR=":"quest2_complete"},"str","^none","/str",{"VAR=":"quest3_status"},"str","^0","/str",{"VAR=":"quest3_progress"},false,{"VAR=":"quest3_complete"},"str","^none","/str",{"VAR=":"quest102_status"},false,{"VAR=":"quest102_complete"},"str","^none","/str",{"VAR=":"quest103_status"},false,{"VAR=":"quest103_complete"},"/ev","end",null],"#f":1}],"listDefs":{}}